fuelcell/__init__.py
fuelcell/data.py
fuelcell/datums.py
fuelcell/docstrings.py
fuelcell/model.py
fuelcell/utils.py
fuelcell/visuals.py
fuelcell-2.0.0.dist-info/LICENSE.txt
fuelcell-2.0.0.dist-info/METADATA
fuelcell-2.0.0.dist-info/WHEEL
fuelcell-2.0.0.dist-info/top_level.txt
fuelcell-2.0.0.dist-info/RECORD
