Metadata-Version: 2.1
Name: fuelcell
Version: 2.0.0
Summary: data processing for fuel cell and electrolyzer experiments
Home-page: https://github.com/samaygarg/fuelcell
Author: Samay Garg
Author-email: samay.garg@berkeley.edu
License: MIT
Project-URL: Documentation, https://fuelcell.readthedocs.io/en/latest/
Project-URL: Source, https://github.com/samaygarg/fuelcell
Keywords: electrochemistry,fuel cell,electrolyzer
Platform: UNKNOWN
Classifier: Development Status :: 4 - Beta
Classifier: Programming Language :: Python :: 3
Requires-Python: >=3
Requires-Dist: numpy
Requires-Dist: pandas
Requires-Dist: matplotlib
